{
  "schema": "code-intel-r06-native-labeled-corpus.v1",
  "labelPolicy": "symbolPresent is a manual semantic label; prediction is at least one native-minimal symbol emitted for the file",
  "samples": [
    { "path": "python_positive.py", "languageClass": "supported", "polarity": "positive", "symbolPresent": true, "content": "# 中文：有效函数\ndef greet(name):\n    return name\n" },
    { "path": "javascript_positive.js", "languageClass": "supported", "polarity": "positive", "symbolPresent": true, "content": "// Español: función real\nfunction saludar(nombre) { return nombre; }\n" },
    { "path": "rust_positive.rs", "languageClass": "supported", "polarity": "positive", "symbolPresent": true, "content": "// 日本語: 実関数\npub fn greet() {}\n" },
    { "path": "go_positive.go", "languageClass": "supported", "polarity": "positive", "symbolPresent": true, "content": "// Português: função real\nfunc Saudacao() {}\n" },
    { "path": "powershell_positive.ps1", "languageClass": "supported", "polarity": "positive", "symbolPresent": true, "content": "# Français : fonction réelle\nfunction Get-Greeting { 'bonjour' }\n" },
    { "path": "java_positive.java", "languageClass": "supported", "polarity": "positive", "symbolPresent": true, "content": "// Deutsch: echte Klasse\npublic class Greeting {}\n" },
    { "path": "python_false_positive.py", "languageClass": "supported", "polarity": "negative", "symbolPresent": false, "content": "TEXT = '''\ndef ghost():\n    pass\n'''\n" },
    { "path": "javascript_false_positive.js", "languageClass": "supported", "polarity": "negative", "symbolPresent": false, "content": "const text = `\nfunction ghost() {}\n`;\n" },
    { "path": "python_false_negative.py", "languageClass": "supported", "polarity": "positive", "symbolPresent": true, "content": "async def fetch_data():\n    return 1\n" },
    { "path": "java_false_negative.java", "languageClass": "supported", "polarity": "positive", "symbolPresent": true, "content": "public String greet() { return \"hi\"; }\n" },
    { "path": "csharp_true_negative.cs", "languageClass": "unsupported", "polarity": "negative", "symbolPresent": false, "content": "// Unsupported language control\npublic class NotClaimed {}\n" },
    { "path": "text_true_negative.txt", "languageClass": "unsupported", "polarity": "negative", "symbolPresent": false, "content": "function words are prose, not code evidence.\n" }
  ]
}
